notesdir/__init__.py
notesdir/__main__.py
notesdir/api.py
notesdir/cli.py
notesdir/conf.py
notesdir/models.py
notesdir/proto.py
notesdir/proto2.py
notesdir/rearrange.py
notesdir/accessors/__init__.py
notesdir/accessors/base.py
notesdir/accessors/delegating.py
notesdir/accessors/html.py
notesdir/accessors/markdown.py
notesdir/accessors/pdf.py
notesdir/repos/__init__.py
notesdir/repos/base.py
notesdir/repos/direct.py
notesdir/repos/sqlite.py
dendron_notesdir-0.0.6.dist-info/LICENSE
dendron_notesdir-0.0.6.dist-info/METADATA
dendron_notesdir-0.0.6.dist-info/WHEEL
dendron_notesdir-0.0.6.dist-info/entry_points.txt
dendron_notesdir-0.0.6.dist-info/top_level.txt
dendron_notesdir-0.0.6.dist-info/RECORD
