Metadata-Version: 2.1
Name: dendron-notesdir
Version: 0.0.6
Summary: Helpers for managing notes as a directory full of files.
Home-page: https://github.com/dendronhq/notesdir
Author: Kevin S Lin
Author-email: kevin@thence.io
License: UNKNOWN
Platform: UNKNOWN
Classifier: Programming Language :: Python :: 3
Classifier: License :: OSI Approved :: MIT License
Classifier: Operating System :: OS Independent
Requires-Python: >=3.7
Requires-Dist: beautifulsoup4 (>=4.9.1)
Requires-Dist: lxml
Requires-Dist: Mako (>=1.1.3)
Requires-Dist: pypdf4
Requires-Dist: pyyaml (>=5.3.1)
Requires-Dist: shortuuid
Requires-Dist: terminaltables
Requires-Dist: python-frontmatter
